Workbook

Sheet Main Data
A2: Row | B2: Order Date | C2: Date | D2: Order ID | E2: Customer Name | F2: Email | G2: Gender | H2: Age | I2: City | J2: State | K2: Zone | L2: Segment | M2: Product Name | N2: Category | O2: SKU | P2: Unit Price | Q2: Qty | R2: Gross Sales | S2: Discount % | T2: Promo Code | U2: Net Revenue | V2: COGS | W2: Gross Profit | X2: Shipping Cost | Y2: Channel | Z2: Campaign | AA2: Spend | AB2: Impressions | AC2: Clicks | AD2: CTR | AE2: Conv. | AF2: ROAS
A3: 1 | B3: 46082 | C3: =TEXT(B3,"DDDD") -> Sunday | D3: LC-4001 | E3: Amit Sharma | F3: amit@email.com | G3: M | H3: 28 | I3: Mumbai | J3: MH | K3: West | L3: New | M3: LipX | N3: Lip Care | O3: LX-01 | P3: 499 | Q3: 2 | R3: 998 | S3: 0.1 | T3: SAVE10 | U3: 898 | V3: 300 | W3: 598 | X3: 50 | Y3: Meta | Z3: Launch_V1 | AA3: 250 | AB3: 5000 | AC3: 150 | AD3: 0.03 | AE3: 1 | AF3: 3.59
A4: 2 | B4: 46082 | C4: =TEXT(B4,"DDDD") -> Sunday | D4: LC-4002 | E4: Priya Das | F4: pri@email.com | G4: F | H4: 24 | I4: Delhi | J4: DL | K4: North | L4: Loyal | M4: Sea Buckthorn | N4: Soap | O4: SB-02 | P4: 350 | Q4: 1 | R4: 350 | S4: 0 | T4: NONE | U4: 350 | V4: 120 | W4: 230 | X4: 60 | Y4: Google | Z4: Search_Br | AA4: 100 | AB4: 2000 | AC4: 80 | AD4: 0.04 | AE4: 1 | AF4: 3.5
A5: 3 | B5: 46083 | C5: =TEXT(B5,"DDDD") -> Monday | D5: LC-4003 | E5: Rahul Varma | F5: r.v@email.com | G5: M | H5: 31 | I5: Bangalore | J5: KA | K5: South | L5: New | M5: Papaya Soap | N5: Soap | O5: PS-01 | P5: 320 | Q5: 3 | R5: 960 | S5: 0.05 | T5: WELCOME | U5: 912 | V5: 270 | W5: 642 | X5: 50 | Y5: Meta | Z5: Retarget | AA5: 200 | AB5: 4500 | AC5: 120 | AD5: 0.026 | AE5: 1 | AF5: 4.56
A6: 4 | B6: 46083 | C6: =TEXT(B6,"DDDD") -> Monday | D6: LC-4004 | E6: Sneha Kapur | F6: sn@email.com | G6: F | H6: 22 | I6: Pune | J6: MH | K6: West | L6: New | M6: Lip Scrub | N6: Lip Care | O6: LS-04 | P6: 299 | Q6: 1 | R6: 299 | S6: 0 | T6: NONE | U6: 299 | V6: 90 | W6: 209 | X6: 40 | Y6: Organic | Z6: N/A | AA6: 0 | AB6: 0 | AC6: 0 | AD6: 0 | AE6: 1 | AF6: 0
A7: 5 | B7: 46084 | C7: =TEXT(B7,"DDDD") -> Tuesday | D7: LC-4005 | E7: Vikram Seth | F7: vik@email.com | G7: M | H7: 35 | I7: Kolkata | J7: WB | K7: East | L7: VIP | M7: LipX | N7: Lip Care | O7: LX-01 | P7: 499 | Q7: 1 | R7: 499 | S7: 0.15 | T7: VIP15 | U7: 424 | V7: 150 | W7: 274 | X7: 70 | Y7: Influencer | Z7: Mar_Collab | AA7: 150 | AB7: 12000 | AC7: 600 | AD7: 0.05 | AE7: 1 | AF7: 2.83
A8: 6 | B8: 46084 | C8: =TEXT(B8,"DDDD") -> Tuesday | D8: LC-4006 | E8: Anjali Nair | F8: anj@email.com | G8: F | H8: 29 | I8: Kochi | J8: KL | K8: South | L8: Loyal | M8: Sea Buckthorn | N8: Soap | O8: SB-02 | P8: 350 | Q8: 2 | R8: 700 | S8: 0.05 | T8: SAVE05 | U8: 665 | V8: 240 | W8: 425 | X8: 60 | Y8: Meta | Z8: Launch_V1 | AA8: 180 | AB8: 3800 | AC8: 110 | AD8: 0.029 | AE8: 1 | AF8: 3.69
A9: 7 | B9: 46085 | C9: =TEXT(B9,"DDDD") -> Wednesday | D9: LC-4007 | E9: Rohan Mehta | F9: roh@email.com | G9: M | H9: 26 | I9: Ahmedabad | J9: GJ | K9: West | L9: New | M9: Papaya Soap | N9: Soap | O9: PS-01 | P9: 320 | Q9: 1 | R9: 320 | S9: 0 | T9: NONE | U9: 320 | V9: 90 | W9: 230 | X9: 50 | Y9: Google | Z9: Search_Gen | AA9: 80 | AB9: 1500 | AC9: 45 | AD9: 0.03 | AE9: 1 | AF9: 4
A10: 8 | B10: 46085 | C10: =TEXT(B10,"DDDD") -> Wednesday | D10: LC-4008 | E10: Ishita Ray | F10: ish@email.com | G10: F | H10: 27 | I10: Hyderabad | J10: TS | K10: South | L10: VIP | M10: Lip Scrub | N10: Lip Care | O10: LS-04 | P10: 299 | Q10: 4 | R10: 1196 | S10: 0.1 | T10: VIP10 | U10: 1076 | V10: 360 | W10: 716 | X10: 50 | Y10: Meta | Z10: Retarget | AA10: 300 | AB10: 6000 | AC10: 200 | AD10: 0.033 | AE10: 1 | AF10: 3.59
A11: 9 | B11: 46086 | C11: =TEXT(B11,"DDDD") -> Thursday | D11: LC-4009 | E11: Kabir Singh | F11: kabir@email.com | G11: M | H11: 30 | I11: Chandigarh | J11: CH | K11: North | L11: New | M11: LipX | N11: Lip Care | O11: LX-01 | P11: 499 | Q11: 1 | R11: 499 | S11: 0 | T11: NONE | U11: 499 | V11: 150 | W11: 349 | X11: 60 | Y11: Organic | Z11: N/A | AA11: 0 | AB11: 0 | AC11: 0 | AD11: 0 | AE11: 1 | AF11: 0
A12: 10 | B12: 46086 | C12: =TEXT(B12,"DDDD") -> Thursday | D12: LC-4010 | E12: Megha Jain | F12: mj@email.com | G12: F | H12: 23 | I12: Jaipur | J12: RJ | K12: North | L12: New | M12: Sea Buckthorn | N12: Soap | O12: SB-02 | P12: 350 | Q12: 2 | R12: 700 | S12: 0.1 | T12: SAVE10 | U12: 630 | V12: 240 | W12: 390 | X12: 60 | Y12: Influencer | Z12: Mar_Collab | AA12: 200 | AB12: 15000 | AC12: 850 | AD12: 0.057 | AE12: 1 | AF12: 3.15

Sheet Homework
B3: ='Main Data'!Y2 -> Channel | C3: ='Main Data'!AF2 -> ROAS | D3: ='Main Data'!AA2 -> Spend
B4: ='Main Data'!Y3 -> Meta | C4: ='Main Data'!AF3 -> 3.59 | D4: ='Main Data'!AA3 -> 250 | U4: Summary
B5: ='Main Data'!Y4 -> Google | C5: ='Main Data'!AF4 -> 3.5 | D5: ='Main Data'!AA4 -> 100
B6: ='Main Data'!Y5 -> Meta | C6: ='Main Data'!AF5 -> 4.56 | D6: ='Main Data'!AA5 -> 200 | J6: ='Main Data'!AA2 -> Spend | K6: ='Main Data'!AC2 -> Clicks | L6: ='Main Data'!AE2 -> Conv. | U6: per click costing = 0.68
B7: ='Main Data'!Y6 -> Organic | C7: ='Main Data'!AF6 -> 0 | D7: ='Main Data'!AA6 -> 0 | J7: ='Main Data'!AA3 -> 250 | K7: ='Main Data'!AC3 -> 150 | L7: ='Main Data'!AE3 -> 1 | P7: Sum of Spend | Q7: Sum of Clicks | R7: Sum of Conv.
B8: ='Main Data'!Y7 -> Influencer | C8: ='Main Data'!AF7 -> 2.83 | D8: ='Main Data'!AA7 -> 150 | J8: ='Main Data'!AA4 -> 100 | K8: ='Main Data'!AC4 -> 80 | L8: ='Main Data'!AE4 -> 1 | P8: 1460 | Q8: 2155 | R8: 10 | U8: one conv cost - 146 (CPA)
B9: ='Main Data'!Y8 -> Meta | C9: ='Main Data'!AF8 -> 3.69 | D9: ='Main Data'!AA8 -> 180 | J9: ='Main Data'!AA5 -> 200 | K9: ='Main Data'!AC5 -> 120 | L9: ='Main Data'!AE5 -> 1
B10: ='Main Data'!Y9 -> Google | C10: ='Main Data'!AF9 -> 4 | D10: ='Main Data'!AA9 -> 80 | J10: ='Main Data'!AA6 -> 0 | K10: ='Main Data'!AC6 -> 0 | L10: ='Main Data'!AE6 -> 1 | U10: 100 conv costing - 14600
B11: ='Main Data'!Y10 -> Meta | C11: ='Main Data'!AF10 -> 3.59 | D11: ='Main Data'!AA10 -> 300 | J11: ='Main Data'!AA7 -> 150 | K11: ='Main Data'!AC7 -> 600 | L11: ='Main Data'!AE7 -> 1
B12: ='Main Data'!Y11 -> Organic | C12: ='Main Data'!AF11 -> 0 | D12: ='Main Data'!AA11 -> 0 | J12: ='Main Data'!AA8 -> 180 | K12: ='Main Data'!AC8 -> 110 | L12: ='Main Data'!AE8 -> 1 | U12: product sell cost - 367 (avg for all product)
B13: ='Main Data'!Y12 -> Influencer | C13: ='Main Data'!AF12 -> 3.15 | D13: ='Main Data'!AA12 -> 200 | J13: ='Main Data'!AA9 -> 80 | K13: ='Main Data'!AC9 -> 45 | L13: ='Main Data'!AE9 -> 1
J14: ='Main Data'!AA10 -> 300 | K14: ='Main Data'!AC10 -> 200 | L14: ='Main Data'!AE10 -> 1 | U14: for 100 - 36700
J15: ='Main Data'!AA11 -> 0 | K15: ='Main Data'!AC11 -> 0 | L15: ='Main Data'!AE11 -> 1
J16: ='Main Data'!AA12 -> 200 | K16: ='Main Data'!AC12 -> 850 | L16: ='Main Data'!AE12 -> 1 | U16: profit-= 36700-14600 = 22100
U18: Shipping cost - avg - 55
U20: RTO - 80
U22: 367-146-55-80 = 86
U23: 86-(COGS - Cost of Good Sold avg) = 86-112
R25: Row Labels | S25: Sum of Spend | T25: Sum of ROAS
R26: Google | S26: 180 | T26: 7.5
R27: Influencer | S27: 350 | T27: 5.98 | U27: Problem
R28: Meta | S28: 930 | T28: 15.43
R29: Organic | S29: 0 | T29: 0 | U29: Reduce CPA
R30: Grand Total | S30: 1460 | T30: 28.91 | U30: Reduce RTO

Sheet Analyse
F1: NEW STRATEGY
A3: CURRENT STATUS | F3: UPDATED VERSION
B4: Item | C4: Cost | D4: Percentage of Sale | F4: Metric | G4: Current Baseline | H4: Improved Model | I4: Impact | M4: Metric | N4: Current (Loss) | O4: Improved (Profit)
B5: Average Sell Price | C5: + ₹367 | D5: 1 | F5: Ad Spend (CPA) | G5: ₹146 | H5: ₹80 | I5: Saved ₹66 | M5: Ad Spend (CPA) | N5: 146 | O5: 80
B6: Marketing (Ads) | C6: - ₹146 | D6: 0.398 | F6: RTO Loss | G6: ₹80 | H6: ₹40 | I6: Saved ₹40 | M6: RTO Loss | N6: 80 | O6: 40
B7: COGS (Manufacturing) | C7: - ₹112 | D7: 0.305 | F7: COGS | G7: ₹112 | H7: ₹112 | I7: No Change | M7: COGS | N7: 112 | O7: 112
B8: RTO (Returns/Losses) | C8: - ₹80 | D8: 0.218 | F8: Shipping | G8: ₹55 | H8: ₹55 | I8: No Change | M8: Shipping | N8: 55 | O8: 55
B9: Shipping | C9: - ₹55 | D9: 0.15 | F9: Total Cost | G9: ₹393 | H9: ₹287 | I9: -27% Expenses
B10: Net Profit | C10: - ₹26 | D10: -7.1% (Loss) | F10: Net Profit/Loss | G10: -₹26 | H10: +₹80 | I10: Flip to Profit
F14: Strategy | G14: Current Setup (High CPA) | H14: New Setup (Target ₹80)
F15: Audience Targeting | G15: Broad interest (e.g., "Skincare") | H15: Custom Lookalike (1% of Buyers)
F16: Retargeting | G16: Not active or very low budget | H16: 70% Budget on Cart Abandoners
F17: Ad Creative | G17: Static product images | H17: UGC (User Generated Content)
F18: Bidding Strategy | G18: Lowest Cost (Auto) | H18: Cost Cap at ₹100
